heist_salt/conf.py
heist_salt/version.py
heist_salt/artifact/salt.py
heist_salt/heist/salt/init.py
heist_salt/heist/salt/master.py
heist_salt/heist/salt/minion.py
heist_salt/heist/salt/proxy.py
heist_salt/salt/init.py
heist_salt/salt/call/init.py
heist_salt/salt/call/contracts/init.py
heist_salt/salt/key/api.py
heist_salt/salt/key/init.py
heist_salt/salt/key/local_master.py
heist_salt/salt/key/raas.py
heist_salt/salt/key/contracts/init.py
heist_salt/salt/pillar/init.py
heist_salt/service/init.py
heist_salt/service/salt/init.py
heist_salt/tool/artifacts.py
heist_salt/tool/config.py
heist_salt/tool/init.py
heist_salt/tool/service.py
heist_salt-7.0.1.dist-info/LICENSE
heist_salt-7.0.1.dist-info/METADATA
heist_salt-7.0.1.dist-info/WHEEL
heist_salt-7.0.1.dist-info/top_level.txt
heist_salt-7.0.1.dist-info/RECORD
