Metadata-Version: 2.1
Name: heist-salt
Version: 7.0.1
Summary: Vertical app-merge components for salt into heist
Home-page: 
Author: Tyler Johnson
Author-email: tyjohnson@vmware.com
Classifier: Operating System :: OS Independent
Classifier: Programming Language :: Python
Classifier: Programming Language :: Python :: 3.9
Classifier: Programming Language :: Python :: 3.10
Classifier: Development Status :: 5 - Production/Stable
Requires-Python: >=3.9
License-File: LICENSE
Requires-Dist: pop >=23.1.0
Requires-Dist: packaging
Requires-Dist: heist >=7.0.1
Requires-Dist: salt >=3006.0rc3
